memory/registers.v
module dtype(D, clk, Q, Qi);
  input  D, clk;
  output reg Q;
  output Qi;

  assign Qi = ~Q;

  always @(posedge clk)
  begin
    Q <= D;
  end
endmodule

module reg8(set, D, Q);
  input  set;
  input  [7:0] D;
  output [7:0] Q;

  reg [7:0] data;

  assign Q = data;

  always @(posedge set) begin
    data <= D;
  end
endmodule

module reg6(set, D, Q, inc, dec);
  input  set;
  input  [5:0] D;
  output [5:0] Q;
  input  inc, dec;

  reg [5:0] data;

  assign Q = data;

  always @(posedge set) begin
    data <= D;
  end

  always @(posedge inc) begin	// There must be a better way to do this
    data++;
  end

  always @(posedge dec) begin
    data--;
  end
endmodule

module reg36(set, D, Q, inc, dec);
  input  set;
  input  [35:0] D;
  output [35:0] Q;
  input  inc, dec;

  reg [35:0] data = 0;

  assign Q = data;

  always @(posedge set) begin
    data <= D;
  end

  always @(posedge inc) begin	// There must be a better way to do this
    data++;
  end

  always @(posedge dec) begin
    data--;
  end
endmodule

module stack64x36(push, D, drop, top, next);
  input  push;		// Push D if high
  input  [35:0] D;
  input  drop;		// Drops an element from the stack (like pop)
  output [35:0] top, next;	// Always output, stored in registers by control unit

  reg [35:0] stack [0:63];	// 64 elements in the stack (2^6)
  reg [5:0] sp;			// Stack pointer

  assign top  = stack[sp];
  assign next = stack[sp-1];

  always @(posedge push) begin
    stack[sp] = D;
    sp++;
  end

  always @(posedge drop) begin
    sp--;
  end
endmodule

memory/tb_reg36.v
module tb_reg36();
  reg set;
  reg [35:0] D;
  wire [35:0] Q;
  reg inc, dec;

  reg36 dut(.set(set), .D(D), .Q(Q), .inc(inc), .dec(dec));

  integer seed = 36;
  initial begin
    $dumpfile("output.vcd");
    $dumpvars(0,tb_reg36);
    set <= 0;
    inc <= 0;
    dec <= 0;
    D <= $urandom(seed)*16 + $urandom(seed)%16;
    #100;
    set <= 1;
    #100;
    D <= $urandom(seed)*16 + $urandom(seed)%16;
    #100;
    D <= $urandom(seed)*16 + $urandom(seed)%16;
    #100;
    D <= $urandom(seed)*16 + $urandom(seed)%16;
    #100;
    set <= 0;
    #100;
    D <= $urandom(seed)*16 + $urandom(seed)%16;
    #100;
    set <= 1;
    #100
    set <=0;
    #100
    inc <= 1;
    #100
    inc <= 0;
    dec <= 1;
    #100 $finish;
  end
endmodule

memory/output.vcd
$date
	Tue Aug 20 16:15:52 2019
$end
$version
	Icarus Verilog
$end
$timescale
	1s
$end
$scope module tb_reg36 $end
$var wire 36 ! Q [35:0] $end
$var reg 36 " D [35:0] $end
$var reg 1 # dec $end
$var reg 1 $ inc $end
$var reg 1 % set $end
$var integer 32 & seed [31:0] $end
$scope module dut $end
$var wire 36 ' D [35:0] $end
$var wire 36 ( Q [35:0] $end
$var wire 1 # dec $end
$var wire 1 $ inc $end
$var wire 1 % set $end
$var reg 36 ) data [35:0] $end
$upscope $end
$upscope $end
$enddefinitions $end
#0
$dumpvars
b0 )
b0 (
b10010111110010000000001000 '
b11111100011100011010101110010010 &
0%
0$
0#
b10010111110010000000001000 "
b0 !
$end
#100
b10010111110010000000001000 !
b10010111110010000000001000 (
b10010111110010000000001000 )
1%
#200
b100110000100111011001111001100001010 "
b100110000100111011001111001100001010 '
b11000101011110101101010000110000 &
#300
b1101000101001001011100011010001101 "
b1101000101001001011100011010001101 '
b1101110111110110010100101111110 &
#400
b110010011011100110100001100100111101 "
b110010011011100110100001100100111101 '
b10010110101010101100011011111100 &
#500
0%
#600
b110011101100000100100001100111111 "
b110011101100000100100001100111111 '
b11001111101100110001010000101010 &
#700
b110011101100000100100001100111111 !
b110011101100000100100001100111111 (
b110011101100000100100001100111111 )
1%
#800
0%
#900
b110011101100000100100001101000000 !
b110011101100000100100001101000000 (
b110011101100000100100001101000000 )
1$
#1000
b110011101100000100100001100111111 !
b110011101100000100100001100111111 (
b110011101100000100100001100111111 )
1#
0$
